viztools/__init__.py
viztools/coordinate_system.py
viztools/utils.py
viztools/controller/__init__.py
viztools/controller/coordinate_system_controller.py
viztools/drawable/__init__.py
viztools/drawable/base_drawable.py
viztools/drawable/draw_utils/__init__.py
viztools/drawable/draw_utils/chunking.py
viztools/drawable/implementations/__init__.py
viztools/drawable/implementations/image.py
viztools/drawable/implementations/lines.py
viztools/drawable/implementations/overlay_text.py
viztools/drawable/implementations/points.py
viztools/ui/__init__.py
viztools/ui/container/__init__.py
viztools/ui/container/base_container.py
viztools/ui/elements/__init__.py
viztools/ui/elements/base_element.py
viztools/ui/elements/implementations/__init__.py
viztools/ui/elements/implementations/button.py
viztools/ui/elements/implementations/checkbox.py
viztools/ui/elements/implementations/edit_field.py
viztools/ui/elements/implementations/label.py
viztools/ui/elements/implementations/slider.py
viztools/ui/elements/implementations/text_field.py
viztools/viewer/__init__.py
viztools/viewer/ui_viewer.py
viztools/viewer/viewer.py
viztools-0.6.8.dist-info/licenses/LICENSE
viztools-0.6.8.dist-info/METADATA
viztools-0.6.8.dist-info/WHEEL
viztools-0.6.8.dist-info/top_level.txt
viztools-0.6.8.dist-info/RECORD
