Metadata-Version: 2.4
Name: viztools
Version: 0.6.8
Summary: Interactively visualize data using pygame.
Author-email: Bruno Schilling <bruno.schilling@protonmail.ch>
License-Expression: MIT
Project-URL: Repository, https://github.com/Bluemi/viztools/tree/main
Requires-Python: >=3.11
License-File: LICENSE
Requires-Dist: numpy>=2.0
Requires-Dist: pygame>=2.6
Requires-Dist: pillow>=10.0
Provides-Extra: dev
Requires-Dist: pytest; extra == "dev"
Requires-Dist: build; extra == "dev"
Requires-Dist: twine; extra == "dev"
Dynamic: license-file
